voice_engine/__init__.py
voice_engine/alsa_source.py
voice_engine/channel_picker.py
voice_engine/dba.py
voice_engine/dbfs.py
voice_engine/delay_sum.py
voice_engine/doa_respeaker_2mic_hat.py
voice_engine/doa_respeaker_4mic_array.py
voice_engine/doa_respeaker_6mic_array.py
voice_engine/doa_respeaker_6p1_mic_array.py
voice_engine/doa_respeaker_v2_6mic_array.py
voice_engine/ec.py
voice_engine/element.py
voice_engine/file_sink.py
voice_engine/file_source.py
voice_engine/gcc_phat.py
voice_engine/kws.py
voice_engine/kws_snowboy.py
voice_engine/ns.py
voice_engine/pyaudio_source.py
voice_engine/raw_file_sink.py
voice_engine/raw_file_source.py
voice_engine/route.py
voice_engine/source.py
voice_engine/vad.py
voice_engine-0.1.3.dist-info/METADATA
voice_engine-0.1.3.dist-info/RECORD
voice_engine-0.1.3.dist-info/WHEEL
voice_engine-0.1.3.dist-info/entry_points.txt
voice_engine-0.1.3.dist-info/top_level.txt
